<?xml version="1.0" encoding="UTF-8"?>
<!DOCTYPE mapper PUBLIC "-//mybatis.org//DTD Mapper 3.0//EN" "http://mybatis.org/dtd/mybatis-3-mapper.dtd">
<mapper namespace="com.dynastech.system.mapper.RoleUserMapper">
  <resultMap id="BaseResultMap" type="com.dynastech.system.entity.RoleUser">
    <!--
      WARNING - @mbggenerated
      This element is automatically generated by MyBatis Generator, do not modify.
      This element was generated on Thu Nov 09 09:25:16 CST 2017.
    -->
    <id column="ru_RoleId" jdbcType="VARCHAR" property="roleid" />
    <id column="ru_UserId" jdbcType="VARCHAR" property="userid" />
    <id column="ru_OrganizationId" jdbcType="VARCHAR" property="organizationid" />
    <result column="ru_Ordinal" jdbcType="INTEGER" property="ordinal" />
    <result column="ru_Sn" jdbcType="INTEGER" property="sn" />
  </resultMap>
  <sql id="Example_Where_Clause">
    <!--
      WARNING - @mbggenerated
      This element is automatically generated by MyBatis Generator, do not modify.
      This element was generated on Thu Nov 09 09:25:16 CST 2017.
    -->
    <where>
      <foreach collection="oredCriteria" item="criteria" separator="or">
        <if test="criteria.valid">
          <trim prefix="(" prefixOverrides="and" suffix=")">
            <foreach collection="criteria.criteria" item="criterion">
              <choose>
                <when test="criterion.noValue">
                  and ${criterion.condition}
                </when>
                <when test="criterion.singleValue">
                  and ${criterion.condition} #{criterion.value}
                </when>
                <when test="criterion.betweenValue">
                  and ${criterion.condition} #{criterion.value} and #{criterion.secondValue}
                </when>
                <when test="criterion.listValue">
                  and ${criterion.condition}
                  <foreach close=")" collection="criterion.value" item="listItem" open="(" separator=",">
                    #{listItem}
                  </foreach>
                </when>
              </choose>
            </foreach>
          </trim>
        </if>
      </foreach>
    </where>
  </sql>
  <sql id="Update_By_Example_Where_Clause">
    <!--
      WARNING - @mbggenerated
      This element is automatically generated by MyBatis Generator, do not modify.
      This element was generated on Thu Nov 09 09:25:16 CST 2017.
    -->
    <where>
      <foreach collection="example.oredCriteria" item="criteria" separator="or">
        <if test="criteria.valid">
          <trim prefix="(" prefixOverrides="and" suffix=")">
            <foreach collection="criteria.criteria" item="criterion">
              <choose>
                <when test="criterion.noValue">
                  and ${criterion.condition}
                </when>
                <when test="criterion.singleValue">
                  and ${criterion.condition} #{criterion.value}
                </when>
                <when test="criterion.betweenValue">
                  and ${criterion.condition} #{criterion.value} and #{criterion.secondValue}
                </when>
                <when test="criterion.listValue">
                  and ${criterion.condition}
                  <foreach close=")" collection="criterion.value" item="listItem" open="(" separator=",">
                    #{listItem}
                  </foreach>
                </when>
              </choose>
            </foreach>
          </trim>
        </if>
      </foreach>
    </where>
  </sql>
  <sql id="Base_Column_List">
    <!--
      WARNING - @mbggenerated
      This element is automatically generated by MyBatis Generator, do not modify.
      This element was generated on Thu Nov 09 09:25:16 CST 2017.
    -->
    ru.RoleId as ru_RoleId, ru.UserId as ru_UserId, ru.OrganizationId as ru_OrganizationId, 
    ru.Ordinal as ru_Ordinal, ru.Sn as ru_Sn
  </sql>
  <select id="selectByExample" parameterType="com.dynastech.system.entity.RoleUserExample" resultMap="BaseResultMap">
    <!--
      WARNING - @mbggenerated
      This element is automatically generated by MyBatis Generator, do not modify.
      This element was generated on Thu Nov 09 09:25:16 CST 2017.
    -->
    select
    <if test="distinct">
      distinct
    </if>
    <include refid="Base_Column_List" />
    from RS_RoleUser ru
    <if test="_parameter != null">
      <include refid="Example_Where_Clause" />
    </if>
    <if test="orderByClause != null">
      order by ${orderByClause}
    </if>
  </select>
  <select id="selectByPrimaryKey" parameterType="com.dynastech.system.entity.RoleUserKey" resultMap="BaseResultMap">
    <!--
      WARNING - @mbggenerated
      This element is automatically generated by MyBatis Generator, do not modify.
      This element was generated on Thu Nov 09 09:25:16 CST 2017.
    -->
    select 
    <include refid="Base_Column_List" />
    from RS_RoleUser ru
    where ru.RoleId = #{roleid,jdbcType=VARCHAR}
      and ru.UserId = #{userid,jdbcType=VARCHAR}
      and ru.OrganizationId = #{organizationid,jdbcType=VARCHAR}
  </select>
  <delete id="deleteByPrimaryKey" parameterType="com.dynastech.system.entity.RoleUserKey">
    <!--
      WARNING - @mbggenerated
      This element is automatically generated by MyBatis Generator, do not modify.
      This element was generated on Thu Nov 09 09:25:16 CST 2017.
    -->
    delete from RS_RoleUser
    where RoleId = #{roleid,jdbcType=VARCHAR}
      and UserId = #{userid,jdbcType=VARCHAR}
      and OrganizationId = #{organizationid,jdbcType=VARCHAR}
  </delete>
  <delete id="deleteByExample" parameterType="com.dynastech.system.entity.RoleUserExample">
    <!--
      WARNING - @mbggenerated
      This element is automatically generated by MyBatis Generator, do not modify.
      This element was generated on Thu Nov 09 09:25:16 CST 2017.
    -->
    delete ru from RS_RoleUser ru
    <if test="_parameter != null">
      <include refid="Example_Where_Clause" />
    </if>
  </delete>
  <insert id="insert" parameterType="com.dynastech.system.entity.RoleUser">
    <!--
      WARNING - @mbggenerated
      This element is automatically generated by MyBatis Generator, do not modify.
      This element was generated on Thu Nov 09 09:25:16 CST 2017.
    -->
    insert into RS_RoleUser (RoleId, UserId, OrganizationId, 
      Ordinal, Sn)
    values (#{roleid,jdbcType=VARCHAR}, #{userid,jdbcType=VARCHAR}, #{organizationid,jdbcType=VARCHAR}, 
      #{ordinal,jdbcType=INTEGER}, #{sn,jdbcType=INTEGER})
  </insert>
  <insert id="insertSelective" parameterType="com.dynastech.system.entity.RoleUser">
    <!--
      WARNING - @mbggenerated
      This element is automatically generated by MyBatis Generator, do not modify.
      This element was generated on Thu Nov 09 09:25:16 CST 2017.
    -->
    insert into RS_RoleUser
    <trim prefix="(" suffix=")" suffixOverrides=",">
      <if test="roleid != null">
        RoleId,
      </if>
      <if test="userid != null">
        UserId,
      </if>
      <if test="organizationid != null">
        OrganizationId,
      </if>
      <if test="ordinal != null">
        Ordinal,
      </if>
      <if test="sn != null">
        Sn,
      </if>
    </trim>
    <trim prefix="values (" suffix=")" suffixOverrides=",">
      <if test="roleid != null">
        #{roleid,jdbcType=VARCHAR},
      </if>
      <if test="userid != null">
        #{userid,jdbcType=VARCHAR},
      </if>
      <if test="organizationid != null">
        #{organizationid,jdbcType=VARCHAR},
      </if>
      <if test="ordinal != null">
        #{ordinal,jdbcType=INTEGER},
      </if>
      <if test="sn != null">
        #{sn,jdbcType=INTEGER},
      </if>
    </trim>
  </insert>
  <select id="countByExample" parameterType="com.dynastech.system.entity.RoleUserExample" resultType="java.lang.Integer">
    <!--
      WARNING - @mbggenerated
      This element is automatically generated by MyBatis Generator, do not modify.
      This element was generated on Thu Nov 09 09:25:16 CST 2017.
    -->
    select count(*) from RS_RoleUser ru
    <if test="_parameter != null">
      <include refid="Example_Where_Clause" />
    </if>
  </select>
  <update id="updateByExampleSelective" parameterType="map">
    <!--
      WARNING - @mbggenerated
      This element is automatically generated by MyBatis Generator, do not modify.
      This element was generated on Thu Nov 09 09:25:16 CST 2017.
    -->
    update RS_RoleUser ru
    <set>
      <if test="record.roleid != null">
        ru.RoleId = #{record.roleid,jdbcType=VARCHAR},
      </if>
      <if test="record.userid != null">
        ru.UserId = #{record.userid,jdbcType=VARCHAR},
      </if>
      <if test="record.organizationid != null">
        ru.OrganizationId = #{record.organizationid,jdbcType=VARCHAR},
      </if>
      <if test="record.ordinal != null">
        ru.Ordinal = #{record.ordinal,jdbcType=INTEGER},
      </if>
      <if test="record.sn != null">
        ru.Sn = #{record.sn,jdbcType=INTEGER},
      </if>
    </set>
    <if test="_parameter != null">
      <include refid="Update_By_Example_Where_Clause" />
    </if>
  </update>
  <update id="updateByExample" parameterType="map">
    <!--
      WARNING - @mbggenerated
      This element is automatically generated by MyBatis Generator, do not modify.
      This element was generated on Thu Nov 09 09:25:16 CST 2017.
    -->
    update RS_RoleUser ru
    set ru.RoleId = #{record.roleid,jdbcType=VARCHAR},
      ru.UserId = #{record.userid,jdbcType=VARCHAR},
      ru.OrganizationId = #{record.organizationid,jdbcType=VARCHAR},
      ru.Ordinal = #{record.ordinal,jdbcType=INTEGER},
      ru.Sn = #{record.sn,jdbcType=INTEGER}
    <if test="_parameter != null">
      <include refid="Update_By_Example_Where_Clause" />
    </if>
  </update>
  <update id="updateByPrimaryKeySelective" parameterType="com.dynastech.system.entity.RoleUser">
    <!--
      WARNING - @mbggenerated
      This element is automatically generated by MyBatis Generator, do not modify.
      This element was generated on Thu Nov 09 09:25:16 CST 2017.
    -->
    update RS_RoleUser
    <set>
      <if test="ordinal != null">
        Ordinal = #{ordinal,jdbcType=INTEGER},
      </if>
      <if test="sn != null">
        Sn = #{sn,jdbcType=INTEGER},
      </if>
    </set>
    where RoleId = #{roleid,jdbcType=VARCHAR}
      and UserId = #{userid,jdbcType=VARCHAR}
      and OrganizationId = #{organizationid,jdbcType=VARCHAR}
  </update>
  <update id="updateByPrimaryKey" parameterType="com.dynastech.system.entity.RoleUser">
    <!--
      WARNING - @mbggenerated
      This element is automatically generated by MyBatis Generator, do not modify.
      This element was generated on Thu Nov 09 09:25:16 CST 2017.
    -->
    update RS_RoleUser
    set Ordinal = #{ordinal,jdbcType=INTEGER},
      Sn = #{sn,jdbcType=INTEGER}
    where RoleId = #{roleid,jdbcType=VARCHAR}
      and UserId = #{userid,jdbcType=VARCHAR}
      and OrganizationId = #{organizationid,jdbcType=VARCHAR}
  </update>
</mapper>